[
  {
    "code": "US_AZ",
    "tenantId": "unitedstatesofamerica.arizona",
    "geometry": {
      "type": "Point",
      "coordinates": [
        -113.384309,
        34.453256
      ]
    }
  },
  {
    "code": "US_AZ_MOHA",
    "tenantId": "unitedstatesofamerica.arizona.mohave",
    "geometry": {
      "type": "Point",
      "coordinates": [
        -113.558318,
        35.62565
      ]
    }
  },
  {
    "code": "US_AZ_LAPA",
    "tenantId": "unitedstatesofamerica.arizona.lapaz",
    "geometry": {
      "type": "Point",
      "coordinates": [
        -114.200738,
        33.889036
      ]
    }
  },
  {
    "code": "US_AZ_COCO",
    "tenantId": "unitedstatesofamerica.arizona.coconino",
    "geometry": {
      "type": "Point",
      "coordinates": [
        -112.498044,
        36.069131
      ]
    }
  },
  {
    "code": "US_AZ_GILA",
    "tenantId": "unitedstatesofamerica.arizona.gila",
    "geometry": {
      "type": "Point",
      "coordinates": [
        -110.873818,
        33.793285
      ]
    }
  },
  {
    "code": "US_AZ_PIMA",
    "tenantId": "unitedstatesofamerica.arizona.pima",
    "geometry": {
      "type": "Point",
      "coordinates": [
        -111.634969,
        32.084673
      ]
    }
  },
  {
    "code": "US_AZ_GREE",
    "tenantId": "unitedstatesofamerica.arizona.greenlee",
    "geometry": {
      "type": "Point",
      "coordinates": [
        -109.179008,
        33.148457
      ]
    }
  },
  {
    "code": "US_AZ_NAVA",
    "tenantId": "unitedstatesofamerica.arizona.navajo",
    "geometry": {
      "type": "Point",
      "coordinates": [
        -110.189217,
        35.137132
      ]
    }
  },
  {
    "code": "US_AZ_YAVA",
    "tenantId": "unitedstatesofamerica.arizona.yavapai",
    "geometry": {
      "type": "Point",
      "coordinates": [
        -112.22694,
        34.625693
      ]
    }
  },
  {
    "code": "US_AZ_CLAR",
    "tenantId": "unitedstatesofamerica.arizona.clark",
    "geometry": {
      "type": "Point",
      "coordinates": [
        -114.639334,
        35.849197
      ]
    }
  },
  {
    "code": "US_AZ_YUMA",
    "tenantId": "unitedstatesofamerica.arizona.yuma",
    "geometry": {
      "type": "Point",
      "coordinates": [
        -114.472995,
        32.808946
      ]
    }
  },
  {
    "code": "US_AZ_PINA",
    "tenantId": "unitedstatesofamerica.arizona.pinal",
    "geometry": {
      "type": "Point",
      "coordinates": [
        -111.209952,
        33.049248
      ]
    }
  },
  {
    "code": "US_AZ_APAC",
    "tenantId": "unitedstatesofamerica.arizona.apache",
    "geometry": {
      "type": "Point",
      "coordinates": [
        -109.434063,
        34.897429
      ]
    }
  },
  {
    "code": "US_AZ_SACR",
    "tenantId": "unitedstatesofamerica.arizona.santacruz",
    "geometry": {
      "type": "Point",
      "coordinates": [
        -110.910492,
        31.524362
      ]
    }
  },
  {
    "code": "US_AZ_COCH",
    "tenantId": "unitedstatesofamerica.arizona.cochise",
    "geometry": {
      "type": "Point",
      "coordinates": [
        -109.610748,
        31.853384
      ]
    }
  },
  {
    "code": "US_AZ_MARI",
    "tenantId": "unitedstatesofamerica.arizona.maricopa",
    "geometry": {
      "type": "Point",
      "coordinates": [
        -111.877499,
        33.602265
      ]
    }
  },
  {
    "code": "US_AZ_GRAH",
    "tenantId": "unitedstatesofamerica.arizona.graham",
    "geometry": {
      "type": "Point",
      "coordinates": [
        -110.126331,
        33.308846
      ]
    }
  }
]