[
  {
    "code": "KR_43",
    "tenantId": "republicofkorea.northchungcheong",
    "geometry": {
      "type": "Point",
      "coordinates": [
        127.840526,
        36.671958
      ]
    }
  },
  {
    "code": "KR_43_EUMS",
    "tenantId": "republicofkorea.northchungcheong.eumseonggun",
    "geometry": {
      "type": "Point",
      "coordinates": [
        127.623896,
        36.973513
      ]
    }
  },
  {
    "code": "KR_43_CHUN",
    "tenantId": "republicofkorea.northchungcheong.chungjusi",
    "geometry": {
      "type": "Point",
      "coordinates": [
        127.904505,
        36.994161
      ]
    }
  },
  {
    "code": "KR_43_JECH",
    "tenantId": "republicofkorea.northchungcheong.jecheonsi",
    "geometry": {
      "type": "Point",
      "coordinates": [
        128.142343,
        37.058675
      ]
    }
  },
  {
    "code": "KR_43_DANY",
    "tenantId": "republicofkorea.northchungcheong.danyanggun",
    "geometry": {
      "type": "Point",
      "coordinates": [
        128.396631,
        36.998938
      ]
    }
  },
  {
    "code": "KR_43_GOES",
    "tenantId": "republicofkorea.northchungcheong.goesangun",
    "geometry": {
      "type": "Point",
      "coordinates": [
        127.85271,
        36.75053
      ]
    }
  },
  {
    "code": "KR_43_JEUN",
    "tenantId": "republicofkorea.northchungcheong.jeungpyeonggun",
    "geometry": {
      "type": "Point",
      "coordinates": [
        127.607305,
        36.77579
      ]
    }
  },
  {
    "code": "KR_43_BOEU",
    "tenantId": "republicofkorea.northchungcheong.boeungun",
    "geometry": {
      "type": "Point",
      "coordinates": [
        127.725696,
        36.477086
      ]
    }
  },
  {
    "code": "KR_43_CHEO",
    "tenantId": "republicofkorea.northchungcheong.cheongjusi",
    "geometry": {
      "type": "Point",
      "coordinates": [
        127.530597,
        36.612171
      ]
    }
  },
  {
    "code": "KR_43_SEJO",
    "tenantId": "republicofkorea.northchungcheong.sejongsi",
    "geometry": {
      "type": "Point",
      "coordinates": [
        127.259848,
        36.559227
      ]
    }
  },
  {
    "code": "KR_43_JINC",
    "tenantId": "republicofkorea.northchungcheong.jincheongun",
    "geometry": {
      "type": "Point",
      "coordinates": [
        127.459956,
        36.871794
      ]
    }
  },
  {
    "code": "KR_43_OKCH",
    "tenantId": "republicofkorea.northchungcheong.okcheongun",
    "geometry": {
      "type": "Point",
      "coordinates": [
        127.661771,
        36.305725
      ]
    }
  },
  {
    "code": "KR_43_YEON",
    "tenantId": "republicofkorea.northchungcheong.yeongdonggun",
    "geometry": {
      "type": "Point",
      "coordinates": [
        127.828229,
        36.170248
      ]
    }
  },
  {
    "code": "KR_43_EUMS_EUMS",
    "tenantId": "republicofkorea.northchungcheong.eumseonggun.eumseongeup",
    "geometry": {
      "type": "Point",
      "coordinates": [
        127.655386,
        36.946708
      ]
    }
  },
  {
    "code": "KR_43_EUMS_GEUM",
    "tenantId": "republicofkorea.northchungcheong.eumseonggun.geumwangeup",
    "geometry": {
      "type": "Point",
      "coordinates": [
        127.562715,
        36.994215
      ]
    }
  },
  {
    "code": "KR_43_EUMS_SOI",
    "tenantId": "republicofkorea.northchungcheong.eumseonggun.soimyeon",
    "geometry": {
      "type": "Point",
      "coordinates": [
        127.756621,
        36.913678
      ]
    }
  },
  {
    "code": "KR_43_EUMS_WONN",
    "tenantId": "republicofkorea.northchungcheong.eumseonggun.wonnammyeon",
    "geometry": {
      "type": "Point",
      "coordinates": [
        127.64395,
        36.87756
      ]
    }
  },
  {
    "code": "KR_43_EUMS_MAEN",
    "tenantId": "republicofkorea.northchungcheong.eumseonggun.maengdongmyeon",
    "geometry": {
      "type": "Point",
      "coordinates": [
        127.553286,
        36.918316
      ]
    }
  },
  {
    "code": "KR_43_EUMS_DAES",
    "tenantId": "republicofkorea.northchungcheong.eumseonggun.daesomyeon",
    "geometry": {
      "type": "Point",
      "coordinates": [
        127.489124,
        36.962943
      ]
    }
  },
  {
    "code": "KR_43_EUMS_SAMS",
    "tenantId": "republicofkorea.northchungcheong.eumseonggun.samseongmyeon",
    "geometry": {
      "type": "Point",
      "coordinates": [
        127.498638,
        37.01691
      ]
    }
  },
  {
    "code": "KR_43_EUMS_SAEN",
    "tenantId": "republicofkorea.northchungcheong.eumseonggun.saenggeukmyeon",
    "geometry": {
      "type": "Point",
      "coordinates": [
        127.612569,
        37.031435
      ]
    }
  },
  {
    "code": "KR_43_EUMS_GAMG",
    "tenantId": "republicofkorea.northchungcheong.eumseonggun.gamgokmyeon",
    "geometry": {
      "type": "Point",
      "coordinates": [
        127.656716,
        37.096075
      ]
    }
  },
  {
    "code": "KR_43_CHUN_JUDE",
    "tenantId": "republicofkorea.northchungcheong.chungjusi.judeokeup",
    "geometry": {
      "type": "Point",
      "coordinates": [
        127.7802,
        36.986867
      ]
    }
  },
  {
    "code": "KR_43_CHUN_SALM",
    "tenantId": "republicofkorea.northchungcheong.chungjusi.salmimyeon",
    "geometry": {
      "type": "Point",
      "coordinates": [
        127.986701,
        36.912258
      ]
    }
  },
  {
    "code": "KR_43_CHUN_SUAN",
    "tenantId": "republicofkorea.northchungcheong.chungjusi.suanbomyeon",
    "geometry": {
      "type": "Point",
      "coordinates": [
        128.037611,
        36.842202
      ]
    }
  },
  {
    "code": "KR_43_CHUN_SINN",
    "tenantId": "republicofkorea.northchungcheong.chungjusi.sinnimyeon",
    "geometry": {
      "type": "Point",
      "coordinates": [
        127.711304,
        36.993913
      ]
    }
  },
  {
    "code": "KR_43_CHUN_NOEU",
    "tenantId": "republicofkorea.northchungcheong.chungjusi.noeunmyeon",
    "geometry": {
      "type": "Point",
      "coordinates": [
        127.752255,
        37.049988
      ]
    }
  },
  {
    "code": "KR_43_CHUN_ANGS",
    "tenantId": "republicofkorea.northchungcheong.chungjusi.angseongmyeon",
    "geometry": {
      "type": "Point",
      "coordinates": [
        127.751706,
        37.126867
      ]
    }
  },
  {
    "code": "KR_43_CHUN_GEUM",
    "tenantId": "republicofkorea.northchungcheong.chungjusi.geumgamyeon",
    "geometry": {
      "type": "Point",
      "coordinates": [
        127.903628,
        37.034673
      ]
    }
  },
  {
    "code": "KR_43_CHUN_DONG",
    "tenantId": "republicofkorea.northchungcheong.chungjusi.dongnyangmyeon",
    "geometry": {
      "type": "Point",
      "coordinates": [
        128.003961,
        37.018801
      ]
    }
  },
  {
    "code": "KR_43_CHUN_SANC",
    "tenantId": "republicofkorea.northchungcheong.chungjusi.sancheokmyeon",
    "geometry": {
      "type": "Point",
      "coordinates": [
        127.998752,
        37.086129
      ]
    }
  },
  {
    "code": "KR_43_CHUN_EOMJ",
    "tenantId": "republicofkorea.northchungcheong.chungjusi.eomjeongmyeon",
    "geometry": {
      "type": "Point",
      "coordinates": [
        127.923187,
        37.10851
      ]
    }
  },
  {
    "code": "KR_43_CHUN_SOTA",
    "tenantId": "republicofkorea.northchungcheong.chungjusi.sotaemyeon",
    "geometry": {
      "type": "Point",
      "coordinates": [
        127.855238,
        37.128131
      ]
    }
  },
  {
    "code": "KR_43_CHUN_DAES",
    "tenantId": "republicofkorea.northchungcheong.chungjusi.daesowonmyeon",
    "geometry": {
      "type": "Point",
      "coordinates": [
        127.861674,
        36.943483
      ]
    }
  },
  {
    "code": "KR_43_CHUN_JUNG",
    "tenantId": "republicofkorea.northchungcheong.chungjusi.jungangtapmyeon",
    "geometry": {
      "type": "Point",
      "coordinates": [
        127.853866,
        37.037427
      ]
    }
  },
  {
    "code": "KR_43_CHUN_SEON",
    "tenantId": "republicofkorea.northchungcheong.chungjusi.seongnaechungindong",
    "geometry": {
      "type": "Point",
      "coordinates": [
        127.934211,
        36.97158
      ]
    }
  },
  {
    "code": "KR_43_CHUN_GYOH",
    "tenantId": "republicofkorea.northchungcheong.chungjusi.gyohyeonallimdong",
    "geometry": {
      "type": "Point",
      "coordinates": [
        127.981482,
        36.979707
      ]
    }
  },
  {
    "code": "KR_43_CHUN_GY2",
    "tenantId": "republicofkorea.northchungcheong.chungjusi.gyohyeonidong",
    "geometry": {
      "type": "Point",
      "coordinates": [
        127.931642,
        36.978545
      ]
    }
  },
  {
    "code": "KR_43_CHUN_YONG",
    "tenantId": "republicofkorea.northchungcheong.chungjusi.yongsandong",
    "geometry": {
      "type": "Point",
      "coordinates": [
        127.944033,
        36.961256
      ]
    }
  },
  {
    "code": "KR_43_CHUN_JIHY",
    "tenantId": "republicofkorea.northchungcheong.chungjusi.jihyeondong",
    "geometry": {
      "type": "Point",
      "coordinates": [
        127.930799,
        36.965693
      ]
    }
  },
  {
    "code": "KR_43_CHUN_MUNH",
    "tenantId": "republicofkorea.northchungcheong.chungjusi.munhwadong",
    "geometry": {
      "type": "Point",
      "coordinates": [
        127.925018,
        36.969171
      ]
    }
  },
  {
    "code": "KR_43_CHUN_HOAM",
    "tenantId": "republicofkorea.northchungcheong.chungjusi.hoamjikdong",
    "geometry": {
      "type": "Point",
      "coordinates": [
        127.950621,
        36.947949
      ]
    }
  },
  {
    "code": "KR_43_CHUN_DALC",
    "tenantId": "republicofkorea.northchungcheong.chungjusi.dalcheondong",
    "geometry": {
      "type": "Point",
      "coordinates": [
        127.897979,
        36.94413
      ]
    }
  },
  {
    "code": "KR_43_CHUN_BONG",
    "tenantId": "republicofkorea.northchungcheong.chungjusi.bongbangdong",
    "geometry": {
      "type": "Point",
      "coordinates": [
        127.90597,
        36.976857
      ]
    }
  },
  {
    "code": "KR_43_CHUN_CHIL",
    "tenantId": "republicofkorea.northchungcheong.chungjusi.chilgeumgeumneungdong",
    "geometry": {
      "type": "Point",
      "coordinates": [
        127.915448,
        36.992167
      ]
    }
  },
  {
    "code": "KR_43_CHUN_YEON",
    "tenantId": "republicofkorea.northchungcheong.chungjusi.yeonsudong",
    "geometry": {
      "type": "Point",
      "coordinates": [
        127.941917,
        36.98928
      ]
    }
  },
  {
    "code": "KR_43_CHUN_MOKA",
    "tenantId": "republicofkorea.northchungcheong.chungjusi.mokaengyongtandong",
    "geometry": {
      "type": "Point",
      "coordinates": [
        127.946055,
        37.009339
      ]
    }
  },
  {
    "code": "KR_43_JECH_BONG",
    "tenantId": "republicofkorea.northchungcheong.jecheonsi.bongyangeup",
    "geometry": {
      "type": "Point",
      "coordinates": [
        128.124109,
        37.152451
      ]
    }
  },
  {
    "code": "KR_43_JECH_GEUM",
    "tenantId": "republicofkorea.northchungcheong.jecheonsi.geumseongmyeon",
    "geometry": {
      "type": "Point",
      "coordinates": [
        128.18654,
        37.067723
      ]
    }
  },
  {
    "code": "KR_43_JECH_CHEO",
    "tenantId": "republicofkorea.northchungcheong.jecheonsi.cheongpungmyeon",
    "geometry": {
      "type": "Point",
      "coordinates": [
        128.143327,
        37.010037
      ]
    }
  },
  {
    "code": "KR_43_JECH_SUSA",
    "tenantId": "republicofkorea.northchungcheong.jecheonsi.susanmyeon",
    "geometry": {
      "type": "Point",
      "coordinates": [
        128.205989,
        36.939089
      ]
    }
  },
  {
    "code": "KR_43_JECH_DEOK",
    "tenantId": "republicofkorea.northchungcheong.jecheonsi.deoksanmyeon",
    "geometry": {
      "type": "Point",
      "coordinates": [
        128.15963,
        36.887174
      ]
    }
  },
  {
    "code": "KR_43_JECH_HANS",
    "tenantId": "republicofkorea.northchungcheong.jecheonsi.hansumyeon",
    "geometry": {
      "type": "Point",
      "coordinates": [
        128.089574,
        36.909036
      ]
    }
  },
  {
    "code": "KR_43_JECH_BAEG",
    "tenantId": "republicofkorea.northchungcheong.jecheonsi.baegunmyeon",
    "geometry": {
      "type": "Point",
      "coordinates": [
        128.01139,
        37.16011
      ]
    }
  },
  {
    "code": "KR_43_JECH_SONG",
    "tenantId": "republicofkorea.northchungcheong.jecheonsi.songhakmyeon",
    "geometry": {
      "type": "Point",
      "coordinates": [
        128.249601,
        37.201834
      ]
    }
  },
  {
    "code": "KR_43_JECH_GYO",
    "tenantId": "republicofkorea.northchungcheong.jecheonsi.gyodong",
    "geometry": {
      "type": "Point",
      "coordinates": [
        128.227842,
        37.150227
      ]
    }
  },
  {
    "code": "KR_43_JECH_YONG",
    "tenantId": "republicofkorea.northchungcheong.jecheonsi.yongdudong",
    "geometry": {
      "type": "Point",
      "coordinates": [
        128.178789,
        37.15201
      ]
    }
  },
  {
    "code": "KR_43_JECH_CHEO2",
    "tenantId": "republicofkorea.northchungcheong.jecheonsi.cheongjeondong",
    "geometry": {
      "type": "Point",
      "coordinates": [
        128.209613,
        37.149762
      ]
    }
  },
  {
    "code": "KR_43_JECH_HWAS",
    "tenantId": "republicofkorea.northchungcheong.jecheonsi.hwasandong",
    "geometry": {
      "type": "Point",
      "coordinates": [
        128.20567,
        37.11208
      ]
    }
  },
  {
    "code": "KR_43_JECH_NAMH",
    "tenantId": "republicofkorea.northchungcheong.jecheonsi.namhyeondong",
    "geometry": {
      "type": "Point",
      "coordinates": [
        128.219911,
        37.13093
      ]
    }
  },
  {
    "code": "KR_43_JECH_YEON",
    "tenantId": "republicofkorea.northchungcheong.jecheonsi.yeongseodong",
    "geometry": {
      "type": "Point",
      "coordinates": [
        128.182842,
        37.128613
      ]
    }
  },
  {
    "code": "KR_43_JECH_SINB",
    "tenantId": "republicofkorea.northchungcheong.jecheonsi.sinbaekdong",
    "geometry": {
      "type": "Point",
      "coordinates": [
        128.258882,
        37.118665
      ]
    }
  },
  {
    "code": "KR_43_JECH_UIRI",
    "tenantId": "republicofkorea.northchungcheong.jecheonsi.uirimjidong",
    "geometry": {
      "type": "Point",
      "coordinates": [
        128.21503,
        37.17137
      ]
    }
  },
  {
    "code": "KR_43_JECH_JUNG",
    "tenantId": "republicofkorea.northchungcheong.jecheonsi.jungangdong",
    "geometry": {
      "type": "Point",
      "coordinates": [
        128.207166,
        37.139489
      ]
    }
  },
  {
    "code": "KR_43_DANY_DANY",
    "tenantId": "republicofkorea.northchungcheong.danyanggun.danyangeup",
    "geometry": {
      "type": "Point",
      "coordinates": [
        128.381197,
        36.960869
      ]
    }
  },
  {
    "code": "KR_43_DANY_MAEP",
    "tenantId": "republicofkorea.northchungcheong.danyanggun.maepoeup",
    "geometry": {
      "type": "Point",
      "coordinates": [
        128.29882,
        37.046068
      ]
    }
  },
  {
    "code": "KR_43_DANY_DANS",
    "tenantId": "republicofkorea.northchungcheong.danyanggun.danseongmyeon",
    "geometry": {
      "type": "Point",
      "coordinates": [
        128.290804,
        36.900418
      ]
    }
  },
  {
    "code": "KR_43_DANY_DAEG",
    "tenantId": "republicofkorea.northchungcheong.danyanggun.daegangmyeon",
    "geometry": {
      "type": "Point",
      "coordinates": [
        128.377003,
        36.872128
      ]
    }
  },
  {
    "code": "KR_43_DANY_GAGO",
    "tenantId": "republicofkorea.northchungcheong.danyanggun.gagokmyeon",
    "geometry": {
      "type": "Point",
      "coordinates": [
        128.43358,
        37.013862
      ]
    }
  },
  {
    "code": "KR_43_DANY_YEON",
    "tenantId": "republicofkorea.northchungcheong.danyanggun.yeongchunmyeon",
    "geometry": {
      "type": "Point",
      "coordinates": [
        128.504055,
        37.077314
      ]
    }
  },
  {
    "code": "KR_43_DANY_EOSA",
    "tenantId": "republicofkorea.northchungcheong.danyanggun.eosangcheonmyeon",
    "geometry": {
      "type": "Point",
      "coordinates": [
        128.341806,
        37.105932
      ]
    }
  },
  {
    "code": "KR_43_DANY_JEOK",
    "tenantId": "republicofkorea.northchungcheong.danyanggun.jeokseongmyeon",
    "geometry": {
      "type": "Point",
      "coordinates": [
        128.273702,
        36.999142
      ]
    }
  },
  {
    "code": "KR_43_GOES_GOES",
    "tenantId": "republicofkorea.northchungcheong.goesangun.goesaneup",
    "geometry": {
      "type": "Point",
      "coordinates": [
        127.813842,
        36.827559
      ]
    }
  },
  {
    "code": "KR_43_GOES_GAMM",
    "tenantId": "republicofkorea.northchungcheong.goesangun.gammulmyeon",
    "geometry": {
      "type": "Point",
      "coordinates": [
        127.87984,
        36.845012
      ]
    }
  },
  {
    "code": "KR_43_GOES_JANG",
    "tenantId": "republicofkorea.northchungcheong.goesangun.jangyeonmyeon",
    "geometry": {
      "type": "Point",
      "coordinates": [
        127.925228,
        36.841337
      ]
    }
  },
  {
    "code": "KR_43_GOES_YEON",
    "tenantId": "republicofkorea.northchungcheong.goesangun.yeonpungmyeon",
    "geometry": {
      "type": "Point",
      "coordinates": [
        128.012238,
        36.769425
      ]
    }
  },
  {
    "code": "KR_43_GOES_CHIL",
    "tenantId": "republicofkorea.northchungcheong.goesangun.chilseongmyeon",
    "geometry": {
      "type": "Point",
      "coordinates": [
        127.873016,
        36.761985
      ]
    }
  },
  {
    "code": "KR_43_GOES_MUNG",
    "tenantId": "republicofkorea.northchungcheong.goesangun.mungwangmyeon",
    "geometry": {
      "type": "Point",
      "coordinates": [
        127.77349,
        36.769316
      ]
    }
  },
  {
    "code": "KR_43_GOES_CHEO",
    "tenantId": "republicofkorea.northchungcheong.goesangun.cheongcheonmyeon",
    "geometry": {
      "type": "Point",
      "coordinates": [
        127.821173,
        36.673596
      ]
    }
  },
  {
    "code": "KR_43_GOES_CHEO2",
    "tenantId": "republicofkorea.northchungcheong.goesangun.cheonganmyeon",
    "geometry": {
      "type": "Point",
      "coordinates": [
        127.686447,
        36.74431
      ]
    }
  },
  {
    "code": "KR_43_GOES_SARI",
    "tenantId": "republicofkorea.northchungcheong.goesangun.sarimyeon",
    "geometry": {
      "type": "Point",
      "coordinates": [
        127.688068,
        36.813711
      ]
    }
  },
  {
    "code": "KR_43_GOES_SOSU",
    "tenantId": "republicofkorea.northchungcheong.goesangun.sosumyeon",
    "geometry": {
      "type": "Point",
      "coordinates": [
        127.725437,
        36.850177
      ]
    }
  },
  {
    "code": "KR_43_GOES_BULJ",
    "tenantId": "republicofkorea.northchungcheong.goesangun.buljeongmyeon",
    "geometry": {
      "type": "Point",
      "coordinates": [
        127.828281,
        36.889379
      ]
    }
  },
  {
    "code": "KR_43_JEUN_JEUN",
    "tenantId": "republicofkorea.northchungcheong.jeungpyeonggun.jeungpyeongeup",
    "geometry": {
      "type": "Point",
      "coordinates": [
        127.606471,
        36.764751
      ]
    }
  },
  {
    "code": "KR_43_JEUN_DOAN",
    "tenantId": "republicofkorea.northchungcheong.jeungpyeonggun.doanmyeon",
    "geometry": {
      "type": "Point",
      "coordinates": [
        127.605853,
        36.830641
      ]
    }
  },
  {
    "code": "KR_43_BOEU_BOEU",
    "tenantId": "republicofkorea.northchungcheong.boeungun.boeuneup",
    "geometry": {
      "type": "Point",
      "coordinates": [
        127.7202,
        36.489457
      ]
    }
  },
  {
    "code": "KR_43_BOEU_SONG",
    "tenantId": "republicofkorea.northchungcheong.boeungun.songnisanmyeon",
    "geometry": {
      "type": "Point",
      "coordinates": [
        127.840158,
        36.52092
      ]
    }
  },
  {
    "code": "KR_43_BOEU_JANG",
    "tenantId": "republicofkorea.northchungcheong.boeungun.janganmyeon",
    "geometry": {
      "type": "Point",
      "coordinates": [
        127.802075,
        36.474319
      ]
    }
  },
  {
    "code": "KR_43_BOEU_MARO",
    "tenantId": "republicofkorea.northchungcheong.boeungun.maromyeon",
    "geometry": {
      "type": "Point",
      "coordinates": [
        127.836335,
        36.414309
      ]
    }
  },
  {
    "code": "KR_43_BOEU_TANB",
    "tenantId": "republicofkorea.northchungcheong.boeungun.tanbumyeon",
    "geometry": {
      "type": "Point",
      "coordinates": [
        127.773513,
        36.439635
      ]
    }
  },
  {
    "code": "KR_43_BOEU_SAMS",
    "tenantId": "republicofkorea.northchungcheong.boeungun.samseungmyeon",
    "geometry": {
      "type": "Point",
      "coordinates": [
        127.735923,
        36.422569
      ]
    }
  },
  {
    "code": "KR_43_BOEU_SUHA",
    "tenantId": "republicofkorea.northchungcheong.boeungun.suhanmyeon",
    "geometry": {
      "type": "Point",
      "coordinates": [
        127.659365,
        36.454447
      ]
    }
  },
  {
    "code": "KR_43_BOEU_HOEN",
    "tenantId": "republicofkorea.northchungcheong.boeungun.hoenammyeon",
    "geometry": {
      "type": "Point",
      "coordinates": [
        127.579224,
        36.426333
      ]
    }
  },
  {
    "code": "KR_43_BOEU_HOEI",
    "tenantId": "republicofkorea.northchungcheong.boeungun.hoeinmyeon",
    "geometry": {
      "type": "Point",
      "coordinates": [
        127.603812,
        36.50277
      ]
    }
  },
  {
    "code": "KR_43_BOEU_NAEB",
    "tenantId": "republicofkorea.northchungcheong.boeungun.naebukmyeon",
    "geometry": {
      "type": "Point",
      "coordinates": [
        127.659329,
        36.552755
      ]
    }
  },
  {
    "code": "KR_43_BOEU_SANO",
    "tenantId": "republicofkorea.northchungcheong.boeungun.sanoemyeon",
    "geometry": {
      "type": "Point",
      "coordinates": [
        127.750876,
        36.576374
      ]
    }
  },
  {
    "code": "KR_43_CHEO_SEOK",
    "tenantId": "republicofkorea.northchungcheong.cheongjusi.seokbongdong",
    "geometry": {
      "type": "Point",
      "coordinates": [
        127.422514,
        36.44925
      ]
    }
  },
  {
    "code": "KR_43_CHEO_NANG",
    "tenantId": "republicofkorea.northchungcheong.cheongjusi.nangseongmyeon",
    "geometry": {
      "type": "Point",
      "coordinates": [
        127.598782,
        36.624914
      ]
    }
  },
  {
    "code": "KR_43_CHEO_MIWO",
    "tenantId": "republicofkorea.northchungcheong.cheongjusi.miwonmyeon",
    "geometry": {
      "type": "Point",
      "coordinates": [
        127.680305,
        36.650731
      ]
    }
  },
  {
    "code": "KR_43_CHEO_GADE",
    "tenantId": "republicofkorea.northchungcheong.cheongjusi.gadeokmyeon",
    "geometry": {
      "type": "Point",
      "coordinates": [
        127.561573,
        36.568519
      ]
    }
  },
  {
    "code": "KR_43_CHEO_NAMI",
    "tenantId": "republicofkorea.northchungcheong.cheongjusi.namilmyeon",
    "geometry": {
      "type": "Point",
      "coordinates": [
        127.52108,
        36.571162
      ]
    }
  },
  {
    "code": "KR_43_CHEO_MUNU",
    "tenantId": "republicofkorea.northchungcheong.cheongjusi.munuimyeon",
    "geometry": {
      "type": "Point",
      "coordinates": [
        127.502346,
        36.487508
      ]
    }
  },
  {
    "code": "KR_43_CHEO_JUNG",
    "tenantId": "republicofkorea.northchungcheong.cheongjusi.jungangdong",
    "geometry": {
      "type": "Point",
      "coordinates": [
        127.49365,
        36.642839
      ]
    }
  },
  {
    "code": "KR_43_CHEO_SEON",
    "tenantId": "republicofkorea.northchungcheong.cheongjusi.seongandong",
    "geometry": {
      "type": "Point",
      "coordinates": [
        127.487986,
        36.631439
      ]
    }
  },
  {
    "code": "KR_43_CHEO_TAP",
    "tenantId": "republicofkorea.northchungcheong.cheongjusi.tapdaeseongdong",
    "geometry": {
      "type": "Point",
      "coordinates": [
        127.496924,
        36.632813
      ]
    }
  },
  {
    "code": "KR_43_CHEO_YEON",
    "tenantId": "republicofkorea.northchungcheong.cheongjusi.yeongundong",
    "geometry": {
      "type": "Point",
      "coordinates": [
        127.50189,
        36.620572
      ]
    }
  },
  {
    "code": "KR_43_CHEO_GEUM",
    "tenantId": "republicofkorea.northchungcheong.cheongjusi.geumcheondong",
    "geometry": {
      "type": "Point",
      "coordinates": [
        127.505524,
        36.628976
      ]
    }
  },
  {
    "code": "KR_43_CHEO_YONG",
    "tenantId": "republicofkorea.northchungcheong.cheongjusi.yongdammyeongamsanseongdong",
    "geometry": {
      "type": "Point",
      "coordinates": [
        127.519888,
        36.644791
      ]
    }
  },
  {
    "code": "KR_43_CHEO_YONG2",
    "tenantId": "republicofkorea.northchungcheong.cheongjusi.yongamdong",
    "geometry": {
      "type": "Point",
      "coordinates": [
        127.521545,
        36.627022
      ]
    }
  },
  {
    "code": "KR_43_CHEO_YONG3",
    "tenantId": "republicofkorea.northchungcheong.cheongjusi.yongamdong",
    "geometry": {
      "type": "Point",
      "coordinates": [
        127.529173,
        36.616225
      ]
    }
  },
  {
    "code": "KR_43_CHEO_NAMI2",
    "tenantId": "republicofkorea.northchungcheong.cheongjusi.namimyeon",
    "geometry": {
      "type": "Point",
      "coordinates": [
        127.430777,
        36.568182
      ]
    }
  },
  {
    "code": "KR_43_CHEO_HYEO",
    "tenantId": "republicofkorea.northchungcheong.cheongjusi.hyeondomyeon",
    "geometry": {
      "type": "Point",
      "coordinates": [
        127.434209,
        36.491967
      ]
    }
  },
  {
    "code": "KR_43_CHEO_SA1",
    "tenantId": "republicofkorea.northchungcheong.cheongjusi.sajikildong",
    "geometry": {
      "type": "Point",
      "coordinates": [
        127.477744,
        36.641685
      ]
    }
  },
  {
    "code": "KR_43_CHEO_SA2",
    "tenantId": "republicofkorea.northchungcheong.cheongjusi.sajikidong",
    "geometry": {
      "type": "Point",
      "coordinates": [
        127.477371,
        36.631812
      ]
    }
  },
  {
    "code": "KR_43_CHEO_SACH",
    "tenantId": "republicofkorea.northchungcheong.cheongjusi.sachangdong",
    "geometry": {
      "type": "Point",
      "coordinates": [
        127.463444,
        36.634299
      ]
    }
  },
  {
    "code": "KR_43_CHEO_MOCH",
    "tenantId": "republicofkorea.northchungcheong.cheongjusi.mochungdong",
    "geometry": {
      "type": "Point",
      "coordinates": [
        127.483055,
        36.625622
      ]
    }
  },
  {
    "code": "KR_43_CHEO_SANN",
    "tenantId": "republicofkorea.northchungcheong.cheongjusi.sannamdong",
    "geometry": {
      "type": "Point",
      "coordinates": [
        127.465578,
        36.608486
      ]
    }
  },
  {
    "code": "KR_43_CHEO_BUNP",
    "tenantId": "republicofkorea.northchungcheong.cheongjusi.bunpyeongdong",
    "geometry": {
      "type": "Point",
      "coordinates": [
        127.48724,
        36.598871
      ]
    }
  },
  {
    "code": "KR_43_CHEO_SU1",
    "tenantId": "republicofkorea.northchungcheong.cheongjusi.sugokildong",
    "geometry": {
      "type": "Point",
      "coordinates": [
        127.484919,
        36.61558
      ]
    }
  },
  {
    "code": "KR_43_CHEO_SU2",
    "tenantId": "republicofkorea.northchungcheong.cheongjusi.sugokidong",
    "geometry": {
      "type": "Point",
      "coordinates": [
        127.474608,
        36.617301
      ]
    }
  },
  {
    "code": "KR_43_CHEO_SEON2",
    "tenantId": "republicofkorea.northchungcheong.cheongjusi.seonghwagaesinjungnimdong",
    "geometry": {
      "type": "Point",
      "coordinates": [
        127.447792,
        36.615643
      ]
    }
  },
  {
    "code": "KR_43_CHEO_OSON",
    "tenantId": "republicofkorea.northchungcheong.cheongjusi.osongeup",
    "geometry": {
      "type": "Point",
      "coordinates": [
        127.319582,
        36.628054
      ]
    }
  },
  {
    "code": "KR_43_CHEO_GANG",
    "tenantId": "republicofkorea.northchungcheong.cheongjusi.gangnaemyeon",
    "geometry": {
      "type": "Point",
      "coordinates": [
        127.366108,
        36.607022
      ]
    }
  },
  {
    "code": "KR_43_CHEO_OKSA",
    "tenantId": "republicofkorea.northchungcheong.cheongjusi.oksanmyeon",
    "geometry": {
      "type": "Point",
      "coordinates": [
        127.374748,
        36.682545
      ]
    }
  },
  {
    "code": "KR_43_CHEO_UNCH",
    "tenantId": "republicofkorea.northchungcheong.cheongjusi.uncheonsinbongdong",
    "geometry": {
      "type": "Point",
      "coordinates": [
        127.470088,
        36.650737
      ]
    }
  },
  {
    "code": "KR_43_CHEO_BO1",
    "tenantId": "republicofkorea.northchungcheong.cheongjusi.bokdaeildong",
    "geometry": {
      "type": "Point",
      "coordinates": [
        127.432256,
        36.640271
      ]
    }
  },
  {
    "code": "KR_43_CHEO_BO2",
    "tenantId": "republicofkorea.northchungcheong.cheongjusi.bokdaeidong",
    "geometry": {
      "type": "Point",
      "coordinates": [
        127.447172,
        36.628817
      ]
    }
  },
  {
    "code": "KR_43_CHEO_GAGY",
    "tenantId": "republicofkorea.northchungcheong.cheongjusi.gagyeongdong",
    "geometry": {
      "type": "Point",
      "coordinates": [
        127.436346,
        36.621401
      ]
    }
  },
  {
    "code": "KR_43_CHEO_BO12",
    "tenantId": "republicofkorea.northchungcheong.cheongjusi.bongmyeongildong",
    "geometry": {
      "type": "Point",
      "coordinates": [
        127.459872,
        36.639717
      ]
    }
  },
  {
    "code": "KR_43_CHEO_BONG",
    "tenantId": "republicofkorea.northchungcheong.cheongjusi.bongmyeongsongjeongdong",
    "geometry": {
      "type": "Point",
      "coordinates": [
        127.451802,
        36.651729
      ]
    }
  },
  {
    "code": "KR_43_CHEO_GA1",
    "tenantId": "republicofkorea.northchungcheong.cheongjusi.gangseoildong",
    "geometry": {
      "type": "Point",
      "coordinates": [
        127.399814,
        36.628334
      ]
    }
  },
  {
    "code": "KR_43_CHEO_GA2",
    "tenantId": "republicofkorea.northchungcheong.cheongjusi.gangseoidong",
    "geometry": {
      "type": "Point",
      "coordinates": [
        127.432089,
        36.662223
      ]
    }
  },
  {
    "code": "KR_43_CHEO_NAES",
    "tenantId": "republicofkorea.northchungcheong.cheongjusi.naesueup",
    "geometry": {
      "type": "Point",
      "coordinates": [
        127.538125,
        36.707333
      ]
    }
  },
  {
    "code": "KR_43_CHEO_OCHA",
    "tenantId": "republicofkorea.northchungcheong.cheongjusi.ochangeup",
    "geometry": {
      "type": "Point",
      "coordinates": [
        127.416228,
        36.729061
      ]
    }
  },
  {
    "code": "KR_43_CHEO_BUGI",
    "tenantId": "republicofkorea.northchungcheong.cheongjusi.bugimyeon",
    "geometry": {
      "type": "Point",
      "coordinates": [
        127.546215,
        36.744639
      ]
    }
  },
  {
    "code": "KR_43_CHEO_OGEU",
    "tenantId": "republicofkorea.northchungcheong.cheongjusi.ogeunjangdong",
    "geometry": {
      "type": "Point",
      "coordinates": [
        127.480034,
        36.69341
      ]
    }
  },
  {
    "code": "KR_43_CHEO_UAM",
    "tenantId": "republicofkorea.northchungcheong.cheongjusi.uamdong",
    "geometry": {
      "type": "Point",
      "coordinates": [
        127.491468,
        36.650588
      ]
    }
  },
  {
    "code": "KR_43_CHEO_NA1",
    "tenantId": "republicofkorea.northchungcheong.cheongjusi.naedeokildong",
    "geometry": {
      "type": "Point",
      "coordinates": [
        127.480921,
        36.658347
      ]
    }
  },
  {
    "code": "KR_43_CHEO_NA2",
    "tenantId": "republicofkorea.northchungcheong.cheongjusi.naedeokidong",
    "geometry": {
      "type": "Point",
      "coordinates": [
        127.496171,
        36.65635
      ]
    }
  },
  {
    "code": "KR_43_CHEO_YULL",
    "tenantId": "republicofkorea.northchungcheong.cheongjusi.yullyangsacheondong",
    "geometry": {
      "type": "Point",
      "coordinates": [
        127.493461,
        36.666421
      ]
    }
  },
  {
    "code": "KR_43_SEJO_JOCH",
    "tenantId": "republicofkorea.northchungcheong.sejongsi.jochiwoneup",
    "geometry": {
      "type": "Point",
      "coordinates": [
        127.292887,
        36.607178
      ]
    }
  },
  {
    "code": "KR_43_SEJO_YEON",
    "tenantId": "republicofkorea.northchungcheong.sejongsi.yeongimyeon",
    "geometry": {
      "type": "Point",
      "coordinates": [
        127.264554,
        36.501081
      ]
    }
  },
  {
    "code": "KR_43_SEJO_YEON2",
    "tenantId": "republicofkorea.northchungcheong.sejongsi.yeondongmyeon",
    "geometry": {
      "type": "Point",
      "coordinates": [
        127.332706,
        36.54954
      ]
    }
  },
  {
    "code": "KR_43_SEJO_BUGA",
    "tenantId": "republicofkorea.northchungcheong.sejongsi.bugangmyeon",
    "geometry": {
      "type": "Point",
      "coordinates": [
        127.374545,
        36.530186
      ]
    }
  },
  {
    "code": "KR_43_SEJO_GEUM",
    "tenantId": "republicofkorea.northchungcheong.sejongsi.geumnammyeon",
    "geometry": {
      "type": "Point",
      "coordinates": [
        127.29878,
        36.460446
      ]
    }
  },
  {
    "code": "KR_43_SEJO_JANG",
    "tenantId": "republicofkorea.northchungcheong.sejongsi.janggunmyeon",
    "geometry": {
      "type": "Point",
      "coordinates": [
        127.210726,
        36.505661
      ]
    }
  },
  {
    "code": "KR_43_SEJO_YEON3",
    "tenantId": "republicofkorea.northchungcheong.sejongsi.yeonseomyeon",
    "geometry": {
      "type": "Point",
      "coordinates": [
        127.250803,
        36.583364
      ]
    }
  },
  {
    "code": "KR_43_SEJO_JEON",
    "tenantId": "republicofkorea.northchungcheong.sejongsi.jeonuimyeon",
    "geometry": {
      "type": "Point",
      "coordinates": [
        127.191925,
        36.663387
      ]
    }
  },
  {
    "code": "KR_43_SEJO_JEON2",
    "tenantId": "republicofkorea.northchungcheong.sejongsi.jeondongmyeon",
    "geometry": {
      "type": "Point",
      "coordinates": [
        127.249561,
        36.660132
      ]
    }
  },
  {
    "code": "KR_43_SEJO_SOJE",
    "tenantId": "republicofkorea.northchungcheong.sejongsi.sojeongmyeon",
    "geometry": {
      "type": "Point",
      "coordinates": [
        127.166857,
        36.713383
      ]
    }
  },
  {
    "code": "KR_43_SEJO_DODA",
    "tenantId": "republicofkorea.northchungcheong.sejongsi.dodamdong",
    "geometry": {
      "type": "Point",
      "coordinates": [
        127.267146,
        36.507055
      ]
    }
  },
  {
    "code": "KR_43_SEJO_JONG",
    "tenantId": "republicofkorea.northchungcheong.sejongsi.jongchondong",
    "geometry": {
      "type": "Point",
      "coordinates": [
        127.245364,
        36.504641
      ]
    }
  },
  {
    "code": "KR_43_SEJO_BORA",
    "tenantId": "republicofkorea.northchungcheong.sejongsi.boramdong",
    "geometry": {
      "type": "Point",
      "coordinates": [
        127.292881,
        36.479996
      ]
    }
  },
  {
    "code": "KR_43_SEJO_AREU",
    "tenantId": "republicofkorea.northchungcheong.sejongsi.areumdong",
    "geometry": {
      "type": "Point",
      "coordinates": [
        127.247116,
        36.52033
      ]
    }
  },
  {
    "code": "KR_43_SEJO_GOUN",
    "tenantId": "republicofkorea.northchungcheong.sejongsi.goundong",
    "geometry": {
      "type": "Point",
      "coordinates": [
        127.241099,
        36.518581
      ]
    }
  },
  {
    "code": "KR_43_SEJO_HANS",
    "tenantId": "republicofkorea.northchungcheong.sejongsi.hansoldong",
    "geometry": {
      "type": "Point",
      "coordinates": [
        127.248297,
        36.472961
      ]
    }
  },
  {
    "code": "KR_43_SEJO_SAER",
    "tenantId": "republicofkorea.northchungcheong.sejongsi.saeromdong",
    "geometry": {
      "type": "Point",
      "coordinates": [
        127.250797,
        36.489361
      ]
    }
  },
  {
    "code": "KR_43_JINC_JINC",
    "tenantId": "republicofkorea.northchungcheong.jincheongun.jincheoneup",
    "geometry": {
      "type": "Point",
      "coordinates": [
        127.423598,
        36.851349
      ]
    }
  },
  {
    "code": "KR_43_JINC_DEOK",
    "tenantId": "republicofkorea.northchungcheong.jincheongun.deoksanmyeon",
    "geometry": {
      "type": "Point",
      "coordinates": [
        127.509209,
        36.895738
      ]
    }
  },
  {
    "code": "KR_43_JINC_CHOP",
    "tenantId": "republicofkorea.northchungcheong.jincheongun.chopyeongmyeon",
    "geometry": {
      "type": "Point",
      "coordinates": [
        127.522297,
        36.828813
      ]
    }
  },
  {
    "code": "KR_43_JINC_MUNB",
    "tenantId": "republicofkorea.northchungcheong.jincheongun.munbaekmyeon",
    "geometry": {
      "type": "Point",
      "coordinates": [
        127.461399,
        36.802294
      ]
    }
  },
  {
    "code": "KR_43_JINC_BAEK",
    "tenantId": "republicofkorea.northchungcheong.jincheongun.baekgokmyeon",
    "geometry": {
      "type": "Point",
      "coordinates": [
        127.351494,
        36.899357
      ]
    }
  },
  {
    "code": "KR_43_JINC_IWOL",
    "tenantId": "republicofkorea.northchungcheong.jincheongun.iwolmyeon",
    "geometry": {
      "type": "Point",
      "coordinates": [
        127.432806,
        36.924018
      ]
    }
  },
  {
    "code": "KR_43_JINC_GWAN",
    "tenantId": "republicofkorea.northchungcheong.jincheongun.gwanghyewonmyeon",
    "geometry": {
      "type": "Point",
      "coordinates": [
        127.430824,
        36.972778
      ]
    }
  },
  {
    "code": "KR_43_OKCH_OKCH",
    "tenantId": "republicofkorea.northchungcheong.okcheongun.okcheoneup",
    "geometry": {
      "type": "Point",
      "coordinates": [
        127.589634,
        36.308056
      ]
    }
  },
  {
    "code": "KR_43_OKCH_DONG",
    "tenantId": "republicofkorea.northchungcheong.okcheongun.dongimyeon",
    "geometry": {
      "type": "Point",
      "coordinates": [
        127.647917,
        36.297856
      ]
    }
  },
  {
    "code": "KR_43_OKCH_ANNA",
    "tenantId": "republicofkorea.northchungcheong.okcheongun.annammyeon",
    "geometry": {
      "type": "Point",
      "coordinates": [
        127.680254,
        36.35534
      ]
    }
  },
  {
    "code": "KR_43_OKCH_ANNA2",
    "tenantId": "republicofkorea.northchungcheong.okcheongun.annaemyeon",
    "geometry": {
      "type": "Point",
      "coordinates": [
        127.641417,
        36.397438
      ]
    }
  },
  {
    "code": "KR_43_OKCH_CHEO",
    "tenantId": "republicofkorea.northchungcheong.okcheongun.cheongseongmyeon",
    "geometry": {
      "type": "Point",
      "coordinates": [
        127.727162,
        36.325004
      ]
    }
  },
  {
    "code": "KR_43_OKCH_CHEO2",
    "tenantId": "republicofkorea.northchungcheong.okcheongun.cheongsanmyeon",
    "geometry": {
      "type": "Point",
      "coordinates": [
        127.812148,
        36.347235
      ]
    }
  },
  {
    "code": "KR_43_OKCH_IWON",
    "tenantId": "republicofkorea.northchungcheong.okcheongun.iwonmyeon",
    "geometry": {
      "type": "Point",
      "coordinates": [
        127.632751,
        36.224761
      ]
    }
  },
  {
    "code": "KR_43_OKCH_GUNS",
    "tenantId": "republicofkorea.northchungcheong.okcheongun.gunseomyeon",
    "geometry": {
      "type": "Point",
      "coordinates": [
        127.528427,
        36.269549
      ]
    }
  },
  {
    "code": "KR_43_OKCH_GUNB",
    "tenantId": "republicofkorea.northchungcheong.okcheongun.gunbukmyeon",
    "geometry": {
      "type": "Point",
      "coordinates": [
        127.558186,
        36.353826
      ]
    }
  },
  {
    "code": "KR_43_YEON_YEON",
    "tenantId": "republicofkorea.northchungcheong.yeongdonggun.yeongdongeup",
    "geometry": {
      "type": "Point",
      "coordinates": [
        127.806007,
        36.181065
      ]
    }
  },
  {
    "code": "KR_43_YEON_YONG",
    "tenantId": "republicofkorea.northchungcheong.yeongdonggun.yongsanmyeon",
    "geometry": {
      "type": "Point",
      "coordinates": [
        127.80038,
        36.260661
      ]
    }
  },
  {
    "code": "KR_43_YEON_HWAN",
    "tenantId": "republicofkorea.northchungcheong.yeongdonggun.hwangganmyeon",
    "geometry": {
      "type": "Point",
      "coordinates": [
        127.896334,
        36.233369
      ]
    }
  },
  {
    "code": "KR_43_YEON_CHUP",
    "tenantId": "republicofkorea.northchungcheong.yeongdonggun.chupungnyeongmyeon",
    "geometry": {
      "type": "Point",
      "coordinates": [
        128.000495,
        36.226523
      ]
    }
  },
  {
    "code": "KR_43_YEON_MAEG",
    "tenantId": "republicofkorea.northchungcheong.yeongdonggun.maegokmyeon",
    "geometry": {
      "type": "Point",
      "coordinates": [
        127.952365,
        36.169053
      ]
    }
  },
  {
    "code": "KR_43_YEON_SANG",
    "tenantId": "republicofkorea.northchungcheong.yeongdonggun.sangchonmyeon",
    "geometry": {
      "type": "Point",
      "coordinates": [
        127.893382,
        36.101848
      ]
    }
  },
  {
    "code": "KR_43_YEON_YANG",
    "tenantId": "republicofkorea.northchungcheong.yeongdonggun.yanggangmyeon",
    "geometry": {
      "type": "Point",
      "coordinates": [
        127.751269,
        36.127056
      ]
    }
  },
  {
    "code": "KR_43_YEON_YONG2",
    "tenantId": "republicofkorea.northchungcheong.yeongdonggun.yonghwamyeon",
    "geometry": {
      "type": "Point",
      "coordinates": [
        127.765813,
        36.040564
      ]
    }
  },
  {
    "code": "KR_43_YEON_HAKS",
    "tenantId": "republicofkorea.northchungcheong.yeongdonggun.haksanmyeon",
    "geometry": {
      "type": "Point",
      "coordinates": [
        127.679923,
        36.089439
      ]
    }
  },
  {
    "code": "KR_43_YEON_YANG2",
    "tenantId": "republicofkorea.northchungcheong.yeongdonggun.yangsanmyeon",
    "geometry": {
      "type": "Point",
      "coordinates": [
        127.643799,
        36.148006
      ]
    }
  },
  {
    "code": "KR_43_YEON_SIMC",
    "tenantId": "republicofkorea.northchungcheong.yeongdonggun.simcheonmyeon",
    "geometry": {
      "type": "Point",
      "coordinates": [
        127.7111,
        36.214349
      ]
    }
  }
]