[
  {
    "code": "CL_RDLL",
    "tenantId": "chile.regindeloslagos",
    "geometry": {
      "type": "Point",
      "coordinates": [
        -73.453871,
        -42.031114
      ]
    }
  },
  {
    "code": "CL_RDLL_PDO",
    "tenantId": "chile.regindeloslagos.provinciadeosorno",
    "geometry": {
      "type": "Point",
      "coordinates": [
        -73.082488,
        -40.772991
      ]
    }
  },
  {
    "code": "CL_RDLL_PDP",
    "tenantId": "chile.regindeloslagos.provinciadepalena",
    "geometry": {
      "type": "Point",
      "coordinates": [
        -72.573004,
        -42.89459
      ]
    }
  },
  {
    "code": "CL_RDLL_PDL",
    "tenantId": "chile.regindeloslagos.provinciadellanquihue",
    "geometry": {
      "type": "Point",
      "coordinates": [
        -72.961535,
        -41.613303
      ]
    }
  },
  {
    "code": "CL_RDLL_PDC",
    "tenantId": "chile.regindeloslagos.provinciadechilo",
    "geometry": {
      "type": "Point",
      "coordinates": [
        -73.749585,
        -42.587884
      ]
    }
  },
  {
    "code": "CL_RDLL_PDO_SAPA",
    "tenantId": "chile.regindeloslagos.provinciadeosorno.sanpablo",
    "geometry": {
      "type": "Point",
      "coordinates": [
        -73.164959,
        -40.443876
      ]
    }
  },
  {
    "code": "CL_RDLL_PDO_OSOR",
    "tenantId": "chile.regindeloslagos.provinciadeosorno.osorno",
    "geometry": {
      "type": "Point",
      "coordinates": [
        -73.169278,
        -40.598217
      ]
    }
  },
  {
    "code": "CL_RDLL_PDO_PURR",
    "tenantId": "chile.regindeloslagos.provinciadeosorno.purranque",
    "geometry": {
      "type": "Point",
      "coordinates": [
        -73.776651,
        -40.937754
      ]
    }
  },
  {
    "code": "CL_RDLL_PDO_PUYE",
    "tenantId": "chile.regindeloslagos.provinciadeosorno.puyehue",
    "geometry": {
      "type": "Point",
      "coordinates": [
        -72.372301,
        -40.705968
      ]
    }
  },
  {
    "code": "CL_RDLL_PDO_RNE",
    "tenantId": "chile.regindeloslagos.provinciadeosorno.ronegro",
    "geometry": {
      "type": "Point",
      "coordinates": [
        -73.696392,
        -40.738318
      ]
    }
  },
  {
    "code": "CL_RDLL_PDO_SJDL",
    "tenantId": "chile.regindeloslagos.provinciadeosorno.sanjuandelacosta",
    "geometry": {
      "type": "Point",
      "coordinates": [
        -73.694261,
        -40.471107
      ]
    }
  },
  {
    "code": "CL_RDLL_PDO_PUOC",
    "tenantId": "chile.regindeloslagos.provinciadeosorno.puertooctay",
    "geometry": {
      "type": "Point",
      "coordinates": [
        -72.474966,
        -40.903877
      ]
    }
  },
  {
    "code": "CL_RDLL_PDP_CHAI",
    "tenantId": "chile.regindeloslagos.provinciadepalena.chaitn",
    "geometry": {
      "type": "Point",
      "coordinates": [
        -72.708018,
        -42.767534
      ]
    }
  },
  {
    "code": "CL_RDLL_PDP_PALE",
    "tenantId": "chile.regindeloslagos.provinciadepalena.palena",
    "geometry": {
      "type": "Point",
      "coordinates": [
        -71.943117,
        -43.673355
      ]
    }
  },
  {
    "code": "CL_RDLL_PDP_FUTA",
    "tenantId": "chile.regindeloslagos.provinciadepalena.futaleuf",
    "geometry": {
      "type": "Point",
      "coordinates": [
        -71.985953,
        -43.181088
      ]
    }
  },
  {
    "code": "CL_RDLL_PDL_FRES",
    "tenantId": "chile.regindeloslagos.provinciadellanquihue.fresia",
    "geometry": {
      "type": "Point",
      "coordinates": [
        -73.82359,
        -41.159735
      ]
    }
  },
  {
    "code": "CL_RDLL_PDL_LLAN",
    "tenantId": "chile.regindeloslagos.provinciadellanquihue.llanquihue",
    "geometry": {
      "type": "Point",
      "coordinates": [
        -73.206646,
        -41.209668
      ]
    }
  },
  {
    "code": "CL_RDLL_PDL_COCH",
    "tenantId": "chile.regindeloslagos.provinciadellanquihue.cocham",
    "geometry": {
      "type": "Point",
      "coordinates": [
        -72.271585,
        -41.710417
      ]
    }
  },
  {
    "code": "CL_RDLL_PDL_LOMU",
    "tenantId": "chile.regindeloslagos.provinciadellanquihue.losmuermos",
    "geometry": {
      "type": "Point",
      "coordinates": [
        -73.779279,
        -41.407538
      ]
    }
  },
  {
    "code": "CL_RDLL_PDL_MAUL",
    "tenantId": "chile.regindeloslagos.provinciadellanquihue.maulln",
    "geometry": {
      "type": "Point",
      "coordinates": [
        -73.655599,
        -41.626099
      ]
    }
  },
  {
    "code": "CL_RDLL_PDL_FRUT",
    "tenantId": "chile.regindeloslagos.provinciadellanquihue.frutillar",
    "geometry": {
      "type": "Point",
      "coordinates": [
        -73.184778,
        -41.041487
      ]
    }
  },
  {
    "code": "CL_RDLL_PDL_PUVA",
    "tenantId": "chile.regindeloslagos.provinciadellanquihue.puertovaras",
    "geometry": {
      "type": "Point",
      "coordinates": [
        -72.445416,
        -41.261067
      ]
    }
  },
  {
    "code": "CL_RDLL_PDL_PUMO",
    "tenantId": "chile.regindeloslagos.provinciadellanquihue.puertomontt",
    "geometry": {
      "type": "Point",
      "coordinates": [
        -72.867564,
        -41.50202
      ]
    }
  },
  {
    "code": "CL_RDLL_PDL_CALB",
    "tenantId": "chile.regindeloslagos.provinciadellanquihue.calbuco",
    "geometry": {
      "type": "Point",
      "coordinates": [
        -73.193573,
        -41.771421
      ]
    }
  },
  {
    "code": "CL_RDLL_PDL_HUAL",
    "tenantId": "chile.regindeloslagos.provinciadellanquihue.hualaihu",
    "geometry": {
      "type": "Point",
      "coordinates": [
        -72.491528,
        -42.101116
      ]
    }
  },
  {
    "code": "CL_RDLL_PDC_PUQU",
    "tenantId": "chile.regindeloslagos.provinciadechilo.puqueldn",
    "geometry": {
      "type": "Point",
      "coordinates": [
        -73.633096,
        -42.640972
      ]
    }
  },
  {
    "code": "CL_RDLL_PDC_ANCU",
    "tenantId": "chile.regindeloslagos.provinciadechilo.ancud",
    "geometry": {
      "type": "Point",
      "coordinates": [
        -73.923894,
        -41.874972
      ]
    }
  },
  {
    "code": "CL_RDLL_PDC_QUEL",
    "tenantId": "chile.regindeloslagos.provinciadechilo.quelln",
    "geometry": {
      "type": "Point",
      "coordinates": [
        -73.937969,
        -43.23321
      ]
    }
  },
  {
    "code": "CL_RDLL_PDC_QUEI",
    "tenantId": "chile.regindeloslagos.provinciadechilo.queiln",
    "geometry": {
      "type": "Point",
      "coordinates": [
        -73.516661,
        -42.869288
      ]
    }
  },
  {
    "code": "CL_RDLL_PDC_CHON",
    "tenantId": "chile.regindeloslagos.provinciadechilo.chonchi",
    "geometry": {
      "type": "Point",
      "coordinates": [
        -73.820291,
        -42.627993
      ]
    }
  },
  {
    "code": "CL_RDLL_PDC_CAST",
    "tenantId": "chile.regindeloslagos.provinciadechilo.castro",
    "geometry": {
      "type": "Point",
      "coordinates": [
        -73.7528,
        -42.474638
      ]
    }
  },
  {
    "code": "CL_RDLL_PDC_DALC",
    "tenantId": "chile.regindeloslagos.provinciadechilo.dalcahue",
    "geometry": {
      "type": "Point",
      "coordinates": [
        -73.714312,
        -42.338218
      ]
    }
  },
  {
    "code": "CL_RDLL_PDC_CDV",
    "tenantId": "chile.regindeloslagos.provinciadechilo.curacodevlez",
    "geometry": {
      "type": "Point",
      "coordinates": [
        -73.582996,
        -42.426299
      ]
    }
  },
  {
    "code": "CL_RDLL_PDC_QUEM",
    "tenantId": "chile.regindeloslagos.provinciadechilo.quemchi",
    "geometry": {
      "type": "Point",
      "coordinates": [
        -73.33802,
        -42.213925
      ]
    }
  },
  {
    "code": "CL_RDLL_PDC_QUIN",
    "tenantId": "chile.regindeloslagos.provinciadechilo.quinchao",
    "geometry": {
      "type": "Point",
      "coordinates": [
        -73.374894,
        -42.522291
      ]
    }
  }
]