[
  {
    "code": "MN",
    "tenantId": "mongolia",
    "geometry": {
      "type": "Point",
      "coordinates": [
        103.379777,
        47.507229
      ]
    }
  },
  {
    "code": "MN_046",
    "tenantId": "mongolia.uvs",
    "geometry": {
      "type": "Point",
      "coordinates": [
        94.092868,
        50.202011
      ]
    }
  },
  {
    "code": "MN_043",
    "tenantId": "mongolia.khovd",
    "geometry": {
      "type": "Point",
      "coordinates": [
        91.857675,
        46.323786
      ]
    }
  },
  {
    "code": "MN_057",
    "tenantId": "mongolia.zavkhan",
    "geometry": {
      "type": "Point",
      "coordinates": [
        96.479729,
        49.49559
      ]
    }
  },
  {
    "code": "MN_067",
    "tenantId": "mongolia.bulgan",
    "geometry": {
      "type": "Point",
      "coordinates": [
        103.403411,
        49.65568
      ]
    }
  },
  {
    "code": "MN_063",
    "tenantId": "mongolia.dornogovi",
    "geometry": {
      "type": "Point",
      "coordinates": [
        110.423113,
        44.000415
      ]
    }
  },
  {
    "code": "MN_1",
    "tenantId": "mongolia.ulaanbaatar",
    "geometry": {
      "type": "Point",
      "coordinates": [
        107.352027,
        47.799872
      ]
    }
  },
  {
    "code": "MN_064",
    "tenantId": "mongolia.govisumber",
    "geometry": {
      "type": "Point",
      "coordinates": [
        108.591624,
        46.492238
      ]
    }
  },
  {
    "code": "MN_051",
    "tenantId": "mongolia.skhbaatar",
    "geometry": {
      "type": "Point",
      "coordinates": [
        113.632414,
        45.657316
      ]
    }
  },
  {
    "code": "MN_065",
    "tenantId": "mongolia.govialtai",
    "geometry": {
      "type": "Point",
      "coordinates": [
        95.350553,
        45.321142
      ]
    }
  },
  {
    "code": "MN_035",
    "tenantId": "mongolia.orkhon",
    "geometry": {
      "type": "Point",
      "coordinates": [
        104.343457,
        49.03363
      ]
    }
  },
  {
    "code": "MN_073",
    "tenantId": "mongolia.arkhangai",
    "geometry": {
      "type": "Point",
      "coordinates": [
        101.022843,
        47.829457
      ]
    }
  },
  {
    "code": "MN_069",
    "tenantId": "mongolia.bayankhongor",
    "geometry": {
      "type": "Point",
      "coordinates": [
        99.50983,
        45.578936
      ]
    }
  },
  {
    "code": "MN_059",
    "tenantId": "mongolia.dundgovi",
    "geometry": {
      "type": "Point",
      "coordinates": [
        106.110439,
        45.512657
      ]
    }
  },
  {
    "code": "MN_053",
    "tenantId": "mongolia.mngovi",
    "geometry": {
      "type": "Point",
      "coordinates": [
        104.174382,
        43.649629
      ]
    }
  },
  {
    "code": "MN_055",
    "tenantId": "mongolia.vrkhangai",
    "geometry": {
      "type": "Point",
      "coordinates": [
        102.869171,
        46.072119
      ]
    }
  },
  {
    "code": "MN_047",
    "tenantId": "mongolia.tv",
    "geometry": {
      "type": "Point",
      "coordinates": [
        106.624625,
        47.796902
      ]
    }
  },
  {
    "code": "MN_061",
    "tenantId": "mongolia.dornod",
    "geometry": {
      "type": "Point",
      "coordinates": [
        117.651349,
        47.649073
      ]
    }
  },
  {
    "code": "MN_049",
    "tenantId": "mongolia.selenge",
    "geometry": {
      "type": "Point",
      "coordinates": [
        106.558694,
        49.895273
      ]
    }
  },
  {
    "code": "MN_041",
    "tenantId": "mongolia.hovsgel",
    "geometry": {
      "type": "Point",
      "coordinates": [
        98.760738,
        50.704568
      ]
    }
  },
  {
    "code": "MN_071",
    "tenantId": "mongolia.bayanlgii",
    "geometry": {
      "type": "Point",
      "coordinates": [
        89.093465,
        48.667102
      ]
    }
  },
  {
    "code": "MN_037",
    "tenantId": "mongolia.darkhanuul",
    "geometry": {
      "type": "Point",
      "coordinates": [
        106.217805,
        49.440757
      ]
    }
  },
  {
    "code": "MN_039",
    "tenantId": "mongolia.khentii",
    "geometry": {
      "type": "Point",
      "coordinates": [
        110.234884,
        48.380878
      ]
    }
  }
]