[
  {
    "code": "US_WA",
    "tenantId": "unitedstatesofamerica.washington",
    "geometry": {
      "type": "Point",
      "coordinates": [
        -122.640673,
        47.798914
      ]
    }
  },
  {
    "code": "US_WA_MASO",
    "tenantId": "unitedstatesofamerica.washington.mason",
    "geometry": {
      "type": "Point",
      "coordinates": [
        -123.025579,
        47.320221
      ]
    }
  },
  {
    "code": "US_WA_PIER",
    "tenantId": "unitedstatesofamerica.washington.pierce",
    "geometry": {
      "type": "Point",
      "coordinates": [
        -122.102509,
        47.136781
      ]
    }
  },
  {
    "code": "US_WA_KING",
    "tenantId": "unitedstatesofamerica.washington.king",
    "geometry": {
      "type": "Point",
      "coordinates": [
        -121.899862,
        47.30919
      ]
    }
  },
  {
    "code": "US_WA_BENT",
    "tenantId": "unitedstatesofamerica.washington.benton",
    "geometry": {
      "type": "Point",
      "coordinates": [
        -119.361842,
        46.230294
      ]
    }
  },
  {
    "code": "US_WA_KITT",
    "tenantId": "unitedstatesofamerica.washington.kittitas",
    "geometry": {
      "type": "Point",
      "coordinates": [
        -120.862004,
        47.405323
      ]
    }
  },
  {
    "code": "US_WA_CHEL",
    "tenantId": "unitedstatesofamerica.washington.chelan",
    "geometry": {
      "type": "Point",
      "coordinates": [
        -120.784165,
        47.639632
      ]
    }
  },
  {
    "code": "US_WA_KITS",
    "tenantId": "unitedstatesofamerica.washington.kitsap",
    "geometry": {
      "type": "Point",
      "coordinates": [
        -122.58223,
        47.690201
      ]
    }
  },
  {
    "code": "US_WA_FERR",
    "tenantId": "unitedstatesofamerica.washington.ferry",
    "geometry": {
      "type": "Point",
      "coordinates": [
        -118.262704,
        48.451242
      ]
    }
  },
  {
    "code": "US_WA_SKAG",
    "tenantId": "unitedstatesofamerica.washington.skagit",
    "geometry": {
      "type": "Point",
      "coordinates": [
        -122.193025,
        48.504664
      ]
    }
  },
  {
    "code": "US_WA_ADAM",
    "tenantId": "unitedstatesofamerica.washington.adams",
    "geometry": {
      "type": "Point",
      "coordinates": [
        -118.30929,
        46.883529
      ]
    }
  },
  {
    "code": "US_WA_DOUG",
    "tenantId": "unitedstatesofamerica.washington.douglas",
    "geometry": {
      "type": "Point",
      "coordinates": [
        -119.675812,
        47.762491
      ]
    }
  },
  {
    "code": "US_WA_KLIC",
    "tenantId": "unitedstatesofamerica.washington.klickitat",
    "geometry": {
      "type": "Point",
      "coordinates": [
        -120.884818,
        45.734778
      ]
    }
  },
  {
    "code": "US_WA_YAKI",
    "tenantId": "unitedstatesofamerica.washington.yakima",
    "geometry": {
      "type": "Point",
      "coordinates": [
        -121.053212,
        46.711582
      ]
    }
  },
  {
    "code": "US_WA_SPOK",
    "tenantId": "unitedstatesofamerica.washington.spokane",
    "geometry": {
      "type": "Point",
      "coordinates": [
        -117.293392,
        47.710934
      ]
    }
  },
  {
    "code": "US_WA_GRAN",
    "tenantId": "unitedstatesofamerica.washington.grant",
    "geometry": {
      "type": "Point",
      "coordinates": [
        -119.610906,
        47.266445
      ]
    }
  },
  {
    "code": "US_WA_PEOR",
    "tenantId": "unitedstatesofamerica.washington.pendoreille",
    "geometry": {
      "type": "Point",
      "coordinates": [
        -117.195991,
        48.497071
      ]
    }
  },
  {
    "code": "US_WA_GRHA",
    "tenantId": "unitedstatesofamerica.washington.graysharbor",
    "geometry": {
      "type": "Point",
      "coordinates": [
        -123.980437,
        47.046568
      ]
    }
  },
  {
    "code": "US_WA_JEFF",
    "tenantId": "unitedstatesofamerica.washington.jefferson",
    "geometry": {
      "type": "Point",
      "coordinates": [
        -123.179663,
        47.890691
      ]
    }
  },
  {
    "code": "US_WA_LINC",
    "tenantId": "unitedstatesofamerica.washington.lincoln",
    "geometry": {
      "type": "Point",
      "coordinates": [
        -118.323294,
        47.825769
      ]
    }
  },
  {
    "code": "US_WA_COLU",
    "tenantId": "unitedstatesofamerica.washington.columbia",
    "geometry": {
      "type": "Point",
      "coordinates": [
        -117.923656,
        46.380109
      ]
    }
  },
  {
    "code": "US_WA_LEWI",
    "tenantId": "unitedstatesofamerica.washington.lewis",
    "geometry": {
      "type": "Point",
      "coordinates": [
        -122.075729,
        46.628837
      ]
    }
  },
  {
    "code": "US_WA_FRAN",
    "tenantId": "unitedstatesofamerica.washington.franklin",
    "geometry": {
      "type": "Point",
      "coordinates": [
        -118.830696,
        46.465258
      ]
    }
  },
  {
    "code": "US_WA_SNOH",
    "tenantId": "unitedstatesofamerica.washington.snohomish",
    "geometry": {
      "type": "Point",
      "coordinates": [
        -121.690762,
        48.022678
      ]
    }
  },
  {
    "code": "US_WA_COWL",
    "tenantId": "unitedstatesofamerica.washington.cowlitz",
    "geometry": {
      "type": "Point",
      "coordinates": [
        -122.727042,
        46.059115
      ]
    }
  },
  {
    "code": "US_WA_CLAR",
    "tenantId": "unitedstatesofamerica.washington.clark",
    "geometry": {
      "type": "Point",
      "coordinates": [
        -122.549322,
        45.765892
      ]
    }
  },
  {
    "code": "US_WA_OKAN",
    "tenantId": "unitedstatesofamerica.washington.okanogan",
    "geometry": {
      "type": "Point",
      "coordinates": [
        -120.099302,
        48.310759
      ]
    }
  },
  {
    "code": "US_WA_THUR",
    "tenantId": "unitedstatesofamerica.washington.thurston",
    "geometry": {
      "type": "Point",
      "coordinates": [
        -122.738991,
        46.98237
      ]
    }
  },
  {
    "code": "US_WA_WHAT",
    "tenantId": "unitedstatesofamerica.washington.whatcom",
    "geometry": {
      "type": "Point",
      "coordinates": [
        -122.186882,
        48.826259
      ]
    }
  },
  {
    "code": "US_WA_WHIT",
    "tenantId": "unitedstatesofamerica.washington.whitman",
    "geometry": {
      "type": "Point",
      "coordinates": [
        -117.620117,
        46.700501
      ]
    }
  },
  {
    "code": "US_WA_SKAM",
    "tenantId": "unitedstatesofamerica.washington.skamania",
    "geometry": {
      "type": "Point",
      "coordinates": [
        -121.934705,
        45.78968
      ]
    }
  },
  {
    "code": "US_WA_ASOT",
    "tenantId": "unitedstatesofamerica.washington.asotin",
    "geometry": {
      "type": "Point",
      "coordinates": [
        -117.05997,
        46.228283
      ]
    }
  },
  {
    "code": "US_WA_WAWA",
    "tenantId": "unitedstatesofamerica.washington.wallawalla",
    "geometry": {
      "type": "Point",
      "coordinates": [
        -118.574218,
        46.225798
      ]
    }
  },
  {
    "code": "US_WA_GARF",
    "tenantId": "unitedstatesofamerica.washington.garfield",
    "geometry": {
      "type": "Point",
      "coordinates": [
        -117.540845,
        46.458149
      ]
    }
  },
  {
    "code": "US_WA_SAJU",
    "tenantId": "unitedstatesofamerica.washington.sanjuan",
    "geometry": {
      "type": "Point",
      "coordinates": [
        -122.989183,
        48.600839
      ]
    }
  },
  {
    "code": "US_WA_STEV",
    "tenantId": "unitedstatesofamerica.washington.stevens",
    "geometry": {
      "type": "Point",
      "coordinates": [
        -118.088152,
        48.400068
      ]
    }
  },
  {
    "code": "US_WA_CLAL",
    "tenantId": "unitedstatesofamerica.washington.clallam",
    "geometry": {
      "type": "Point",
      "coordinates": [
        -123.996542,
        48.170122
      ]
    }
  },
  {
    "code": "US_WA_ISLA",
    "tenantId": "unitedstatesofamerica.washington.island",
    "geometry": {
      "type": "Point",
      "coordinates": [
        -122.525029,
        48.156345
      ]
    }
  },
  {
    "code": "US_WA_PACI",
    "tenantId": "unitedstatesofamerica.washington.pacific",
    "geometry": {
      "type": "Point",
      "coordinates": [
        -123.933022,
        46.539269
      ]
    }
  }
]