[
  {
    "tenantId": "iranislamicrepublicof",
    "code": "IR",
    "hierarchyType": "ADMIN",
    "boundaryType": "Country",
    "parent": null
  },
  {
    "tenantId": "iranislamicrepublicof.mazandaran",
    "code": "IR_21",
    "hierarchyType": "ADMIN",
    "boundaryType": "State",
    "parent": "IR"
  },
  {
    "tenantId": "iranislamicrepublicof.northkhorasan",
    "code": "IR_31",
    "hierarchyType": "ADMIN",
    "boundaryType": "State",
    "parent": "IR"
  },
  {
    "tenantId": "iranislamicrepublicof.kerman",
    "code": "IR_15",
    "hierarchyType": "ADMIN",
    "boundaryType": "State",
    "parent": "IR"
  },
  {
    "tenantId": "iranislamicrepublicof.ilam",
    "code": "IR_05",
    "hierarchyType": "ADMIN",
    "boundaryType": "State",
    "parent": "IR"
  },
  {
    "tenantId": "iranislamicrepublicof.lorestan",
    "code": "IR_20",
    "hierarchyType": "ADMIN",
    "boundaryType": "State",
    "parent": "IR"
  },
  {
    "tenantId": "iranislamicrepublicof.markazi",
    "code": "IR_22",
    "hierarchyType": "ADMIN",
    "boundaryType": "State",
    "parent": "IR"
  },
  {
    "tenantId": "iranislamicrepublicof.chaharmahalandbakhtiari",
    "code": "IR_08",
    "hierarchyType": "ADMIN",
    "boundaryType": "State",
    "parent": "IR"
  },
  {
    "tenantId": "iranislamicrepublicof.kermanshah",
    "code": "IR_17",
    "hierarchyType": "ADMIN",
    "boundaryType": "State",
    "parent": "IR"
  },
  {
    "tenantId": "iranislamicrepublicof.hamadan",
    "code": "IR_24",
    "hierarchyType": "ADMIN",
    "boundaryType": "State",
    "parent": "IR"
  },
  {
    "tenantId": "iranislamicrepublicof.qazvin",
    "code": "IR_28",
    "hierarchyType": "ADMIN",
    "boundaryType": "State",
    "parent": "IR"
  },
  {
    "tenantId": "iranislamicrepublicof.gilan",
    "code": "IR_19",
    "hierarchyType": "ADMIN",
    "boundaryType": "State",
    "parent": "IR"
  },
  {
    "tenantId": "iranislamicrepublicof.zanjan",
    "code": "IR_11",
    "hierarchyType": "ADMIN",
    "boundaryType": "State",
    "parent": "IR"
  },
  {
    "tenantId": "iranislamicrepublicof.semnan",
    "code": "IR_12",
    "hierarchyType": "ADMIN",
    "boundaryType": "State",
    "parent": "IR"
  },
  {
    "tenantId": "iranislamicrepublicof.isfahan",
    "code": "IR_04",
    "hierarchyType": "ADMIN",
    "boundaryType": "State",
    "parent": "IR"
  },
  {
    "tenantId": "iranislamicrepublicof.kohgiluyehandboyerahmad",
    "code": "IR_18",
    "hierarchyType": "ADMIN",
    "boundaryType": "State",
    "parent": "IR"
  },
  {
    "tenantId": "iranislamicrepublicof.kurdistan",
    "code": "IR_16",
    "hierarchyType": "ADMIN",
    "boundaryType": "State",
    "parent": "IR"
  },
  {
    "tenantId": "iranislamicrepublicof.westazerbaijan",
    "code": "IR_02",
    "hierarchyType": "ADMIN",
    "boundaryType": "State",
    "parent": "IR"
  },
  {
    "tenantId": "iranislamicrepublicof.fars",
    "code": "IR_14",
    "hierarchyType": "ADMIN",
    "boundaryType": "State",
    "parent": "IR"
  },
  {
    "tenantId": "iranislamicrepublicof.bushehr",
    "code": "IR_06",
    "hierarchyType": "ADMIN",
    "boundaryType": "State",
    "parent": "IR"
  },
  {
    "tenantId": "iranislamicrepublicof.ardabil",
    "code": "IR_03",
    "hierarchyType": "ADMIN",
    "boundaryType": "State",
    "parent": "IR"
  },
  {
    "tenantId": "iranislamicrepublicof.golestan",
    "code": "IR_27",
    "hierarchyType": "ADMIN",
    "boundaryType": "State",
    "parent": "IR"
  },
  {
    "tenantId": "iranislamicrepublicof.razavikhorasan",
    "code": "IR_30",
    "hierarchyType": "ADMIN",
    "boundaryType": "State",
    "parent": "IR"
  },
  {
    "tenantId": "iranislamicrepublicof.southkhorasan",
    "code": "IR_29",
    "hierarchyType": "ADMIN",
    "boundaryType": "State",
    "parent": "IR"
  },
  {
    "tenantId": "iranislamicrepublicof.sistanandbaluchestan",
    "code": "IR_13",
    "hierarchyType": "ADMIN",
    "boundaryType": "State",
    "parent": "IR"
  },
  {
    "tenantId": "iranislamicrepublicof.qom",
    "code": "IR_26",
    "hierarchyType": "ADMIN",
    "boundaryType": "State",
    "parent": "IR"
  },
  {
    "tenantId": "iranislamicrepublicof.alborz",
    "code": "IR_09",
    "hierarchyType": "ADMIN",
    "boundaryType": "State",
    "parent": "IR"
  },
  {
    "tenantId": "iranislamicrepublicof.eastazerbaijan",
    "code": "IR_01",
    "hierarchyType": "ADMIN",
    "boundaryType": "State",
    "parent": "IR"
  },
  {
    "tenantId": "iranislamicrepublicof.yazd",
    "code": "IR_25",
    "hierarchyType": "ADMIN",
    "boundaryType": "State",
    "parent": "IR"
  },
  {
    "tenantId": "iranislamicrepublicof.hormozgan",
    "code": "IR_23",
    "hierarchyType": "ADMIN",
    "boundaryType": "State",
    "parent": "IR"
  },
  {
    "tenantId": "iranislamicrepublicof.khuzestan",
    "code": "IR_10",
    "hierarchyType": "ADMIN",
    "boundaryType": "State",
    "parent": "IR"
  },
  {
    "tenantId": "iranislamicrepublicof.tehran",
    "code": "IR_TEHR",
    "hierarchyType": "ADMIN",
    "boundaryType": "State",
    "parent": "IR"
  },
  {
    "tenantId": "iranislamicrepublicof.mazandaran",
    "code": "IR_212",
    "hierarchyType": "ADMIN",
    "boundaryType": "State",
    "parent": "IR"
  }
]